[
    {
      "date": "2015-10-01",
      "events": [
        {
          "time": "2015-10-02 10:00:00",
          "content": "HR new hire orientation"
        },
        {
          "time": "2015-10-02 11:00:00",
          "content": "Xingyii stand up"
        },
        {
          "time": "2015-10-02 12:00:00",
          "content": "Android core meeting"
        },
        {
          "time": "2015-10-02 13:00:00",
          "content": "Code review"
        },
        {
          "time": "2015-10-02 14:00:00",
          "content": "Breakfast time"
        },
        {
          "time": "2015-10-02 15:30:00",
          "content": "4B meeting talk"
        },
        {
          "time": "2015-10-02 16:00:00",
          "content": "Breakfast time"
        },
        {
          "time": "2015-10-02 17:30:00",
          "content": "4B meeting talk"
        },
        {
          "time": "2015-10-02 19:00:00",
          "content": "Breakfast time"
        },
        {
          "time": "2015-10-02 20:30:00",
          "content": "4B meeting talk"
        }
      ]
    },
    {
      "date": "2015-10-02",
      "events": [
        {
          "time": "2015-10-02 19:00:00",
          "content": "Breakfast time"
        },
        {
          "time": "2015-10-02 20:30:00",
          "content": "4B meeting talk"
        }
      ]
    },
    {
      "date": "2015-10-02",
      "events": [
        {
          "time": "2015-10-02 21:00:00",
          "content": "Recruiting time"
        },
        {
          "time": "2015-10-02 22:00:00",
          "content": "Code review"
        }
      ]
    },
    {
      "date": "2015-10-03",
      "events": [
        {
          "time": "2015-10-03 12:00:00",
          "content": "Team building at Xi'an Fanzhuang"
        }
      ]
    },
    {
      "date": "2015-10-03",
      "events": [
        {
          "time": "2015-10-03 9:00:00",
          "content": "Pick up friends"
        },
        {
          "time": "2015-02-13 20:00:00",
          "content": "Dinner time with wife"
        }
      ]
    },
    {
      "date": "2015-02-20",
      "events": [
        {
          "time": "2015-02-20 10:00:00",
          "content": "Buy gift for parents"
        },
        {
          "time": "2015-02-20 11:00:00",
          "content": "Go shopping"
        },
        {
          "time": "2015-02-20 12:00:00",
          "content": "Have a rest"
        },
        {
          "time": "2015-02-20 15:00:00",
          "content": "Listen to music"
        },
        {
          "time": "2015-02-20 18:00:00",
          "content": "Exercise time"
        }
      ]
    },
    {
      "date": "2015-02-25",
      "events": [
        {
          "time": "2015-02-25 20:00:00",
          "content": "Merry Christmas to you"
        }
      ]
    }
  ]